radius_plugins/erc20/__init__.py
radius_plugins/erc20/abi.py
radius_plugins/erc20/parameters.py
radius_plugins/erc20/service.py
radius_plugins/erc20/token.py
radius_ai_agent_sdk_plugin_erc20-1.0.0.dist-info/METADATA
radius_ai_agent_sdk_plugin_erc20-1.0.0.dist-info/WHEEL
radius_ai_agent_sdk_plugin_erc20-1.0.0.dist-info/top_level.txt
radius_ai_agent_sdk_plugin_erc20-1.0.0.dist-info/RECORD
