Metadata-Version: 2.2
Name: radius-ai-agent-sdk-plugin-erc20
Version: 1.0.0
Summary: Radius plugin for ERC20
Author-email: Matt Dionis <matt.dionis@radiustechnologysystems.com>
License: MIT
Project-URL: Homepage, https://github.com/radiustechsystems/ai-agent-toolkit
Project-URL: Documentation, https://github.com/radiustechsystems/ai-agent-toolkit/blob/main/python/src/plugins/erc20/README.md
Project-URL: Repository, https://github.com/radiustechsystems/ai-agent-toolkit/blob/main/python/src/plugins/erc20
Project-URL: Issues, https://github.com/radiustechsystems/ai-agent-toolkit/issues
Project-URL: Changelog, https://github.com/radiustechsystems/ai-agent-toolkit/blob/main/python/CHANGELOG.md
Keywords: radius,sdk,web3,agents,ai
Classifier: Development Status :: 3 - Alpha
Classifier: Intended Audience :: Developers
Classifier: License :: OSI Approved :: MIT License
Classifier: Programming Language :: Python :: 3
Classifier: Programming Language :: Python :: 3.10
Classifier: Programming Language :: Python :: 3.11
Classifier: Programming Language :: Python :: 3.12
Requires-Python: >=3.10
Requires-Dist: radius-ai-agent-sdk>=1.0.0
Requires-Dist: radius-ai-agent-sdk-wallet-evm>=1.0.0
Provides-Extra: dev
Requires-Dist: ruff>=0.8.6; extra == "dev"
Requires-Dist: pytest>=8.3.4; extra == "dev"
Requires-Dist: pytest-asyncio>=0.25.0; extra == "dev"
